itslive/__init__.py
itslive/cli/__init__.py
itslive/cli/export.py
itslive/cli/plot.py
itslive/dataviz/__init__.py
itslive/dataviz/_viz.py
itslive/velocity_cubes/__init__.py
itslive/velocity_cubes/_cubes.py
itslive/velocity_pairs/__init__.py
itslive/velocity_pairs/_pairs.py
itslive-0.3.2.dist-info/LICENSE
itslive-0.3.2.dist-info/METADATA
itslive-0.3.2.dist-info/WHEEL
itslive-0.3.2.dist-info/entry_points.txt
itslive-0.3.2.dist-info/RECORD
